McSixRu/__init__.py
McSixRu/core.py
McSixRu-1.0.3.dist-info/METADATA
McSixRu-1.0.3.dist-info/WHEEL
McSixRu-1.0.3.dist-info/top_level.txt
McSixRu-1.0.3.dist-info/RECORD
