Metadata-Version: 2.1
Name: McSixRu
Version: 1.0.3
Summary: AI library for Russian users with OpenRouter integration
Author: McSIxRu
Author-email: mcsixhelps@gmail.com
Keywords: ai,chat,openrouter,russian
Classifier: Programming Language :: Python :: 3
Classifier: License :: OSI Approved :: MIT License
Classifier: Operating System :: OS Independent
Requires-Python: >=3.6
Requires-Dist: requests >=2.25.0
